jupyterlab_server_proxy_launcher_fix/__init__.py
jupyterlab_server_proxy_launcher_fix/_version.py
jupyterlab_server_proxy_launcher_fix/routes.py
jupyterlab_server_proxy_launcher_fix/tests/__init__.py
jupyterlab_server_proxy_launcher_fix/tests/test_routes.py
jupyterlab_server_proxy_launcher_fix-1.0.4.data/data/etc/jupyter/jupyter_server_config.d/jupyterlab_server_proxy_launcher_fix.json
jupyterlab_server_proxy_launcher_fix-1.0.4.data/data/share/jupyter/labextensions/jupyterlab_server_proxy_launcher_fix/package.json
jupyterlab_server_proxy_launcher_fix-1.0.4.data/data/share/jupyter/labextensions/jupyterlab_server_proxy_launcher_fix/schemas/jupyterlab_server_proxy_launcher_fix/package.json.orig
jupyterlab_server_proxy_launcher_fix-1.0.4.data/data/share/jupyter/labextensions/jupyterlab_server_proxy_launcher_fix/schemas/jupyterlab_server_proxy_launcher_fix/plugin.json
jupyterlab_server_proxy_launcher_fix-1.0.4.data/data/share/jupyter/labextensions/jupyterlab_server_proxy_launcher_fix/static/555.79d2df098c3e3710d576.js
jupyterlab_server_proxy_launcher_fix-1.0.4.data/data/share/jupyter/labextensions/jupyterlab_server_proxy_launcher_fix/static/728.1585f5e889acaa578435.js
jupyterlab_server_proxy_launcher_fix-1.0.4.data/data/share/jupyter/labextensions/jupyterlab_server_proxy_launcher_fix/static/remoteEntry.517d4d9baa5858cc4d09.js
jupyterlab_server_proxy_launcher_fix-1.0.4.data/data/share/jupyter/labextensions/jupyterlab_server_proxy_launcher_fix/static/style.js
jupyterlab_server_proxy_launcher_fix-1.0.4.data/data/share/jupyter/labextensions/jupyterlab_server_proxy_launcher_fix/static/third-party-licenses.json
jupyterlab_server_proxy_launcher_fix-1.0.4.data/data/share/jupyter/labextensions/jupyterlab_server_proxy_launcher_fix/install.json
jupyterlab_server_proxy_launcher_fix-1.0.4.dist-info/METADATA
jupyterlab_server_proxy_launcher_fix-1.0.4.dist-info/WHEEL
jupyterlab_server_proxy_launcher_fix-1.0.4.dist-info/licenses/LICENSE
jupyterlab_server_proxy_launcher_fix-1.0.4.dist-info/RECORD
