Metadata-Version: 2.4
Name: jupyterlab_server_proxy_launcher_fix
Version: 1.0.4
Summary: Fix to the issue that when launchers configured in the jupyter config file with svg icons are in a different category than notebooks, icons are not displayed
Project-URL: Homepage, https://github.com/stellarshenson/jupyterlab_server_proxy_launcher_fix
Project-URL: Bug Tracker, https://github.com/stellarshenson/jupyterlab_server_proxy_launcher_fix/issues
Project-URL: Repository, https://github.com/stellarshenson/jupyterlab_server_proxy_launcher_fix.git
Author-email: Stellars Henson <konrad.jelen@gmail.com>
License: BSD 3-Clause License
License-File: LICENSE
Keywords: jupyter,jupyterlab,jupyterlab-extension
Classifier: Framework :: Jupyter
Classifier: Framework :: Jupyter :: JupyterLab
Classifier: Framework :: Jupyter :: JupyterLab :: 4
Classifier: Framework :: Jupyter :: JupyterLab :: Extensions
Classifier: Framework :: Jupyter :: JupyterLab :: Extensions :: Prebuilt
Classifier: License :: OSI Approved :: BSD License
Classifier: Programming Language :: Python
Classifier: Programming Language :: Python :: 3
Classifier: Programming Language :: Python :: 3.10
Classifier: Programming Language :: Python :: 3.11
Classifier: Programming Language :: Python :: 3.12
Classifier: Programming Language :: Python :: 3.13
Classifier: Programming Language :: Python :: 3.14
Requires-Python: >=3.10
Requires-Dist: jupyter-server-proxy>=4.0.0
Provides-Extra: dev
Requires-Dist: jupyterlab>=4; extra == 'dev'
Provides-Extra: test
Requires-Dist: coverage; extra == 'test'
Requires-Dist: pytest; extra == 'test'
Requires-Dist: pytest-asyncio; extra == 'test'
Requires-Dist: pytest-cov; extra == 'test'
Requires-Dist: pytest-jupyter[server]>=0.6.0; extra == 'test'
